odoo/addons/mis_builder_cash_flow/README.rst
odoo/addons/mis_builder_cash_flow/__init__.py
odoo/addons/mis_builder_cash_flow/__manifest__.py
odoo/addons/mis_builder_cash_flow/data/mis_report.xml
odoo/addons/mis_builder_cash_flow/data/mis_report_instance.xml
odoo/addons/mis_builder_cash_flow/data/mis_report_style.xml
odoo/addons/mis_builder_cash_flow/i18n/ca.po
odoo/addons/mis_builder_cash_flow/i18n/ca_ES.po
odoo/addons/mis_builder_cash_flow/i18n/es.po
odoo/addons/mis_builder_cash_flow/i18n/es_AR.po
odoo/addons/mis_builder_cash_flow/i18n/it.po
odoo/addons/mis_builder_cash_flow/i18n/mis_builder_cash_flow.pot
odoo/addons/mis_builder_cash_flow/i18n/nl.po
odoo/addons/mis_builder_cash_flow/i18n/pt.po
odoo/addons/mis_builder_cash_flow/i18n/pt_BR.po
odoo/addons/mis_builder_cash_flow/i18n/sv.po
odoo/addons/mis_builder_cash_flow/models/__init__.py
odoo/addons/mis_builder_cash_flow/models/account_account.py
odoo/addons/mis_builder_cash_flow/models/mis_cash_flow_forecast_line.py
odoo/addons/mis_builder_cash_flow/models/mis_report_instance.py
odoo/addons/mis_builder_cash_flow/readme/CONTRIBUTORS.rst
odoo/addons/mis_builder_cash_flow/readme/DESCRIPTION.rst
odoo/addons/mis_builder_cash_flow/readme/ROADMAP.rst
odoo/addons/mis_builder_cash_flow/readme/USAGE.rst
odoo/addons/mis_builder_cash_flow/report/__init__.py
odoo/addons/mis_builder_cash_flow/report/mis_cash_flow.py
odoo/addons/mis_builder_cash_flow/report/mis_cash_flow_views.xml
odoo/addons/mis_builder_cash_flow/security/mis_cash_flow_security.xml
odoo/addons/mis_builder_cash_flow/static/description/icon.png
odoo/addons/mis_builder_cash_flow/static/description/index.html
odoo/addons/mis_builder_cash_flow/tests/__init__.py
odoo/addons/mis_builder_cash_flow/tests/test_cash_flow.py
odoo/addons/mis_builder_cash_flow/views/account_account_views.xml
odoo/addons/mis_builder_cash_flow/views/mis_cash_flow_forecast_line_views.xml
odoo14_addon_mis_builder_cash_flow-14.0.1.0.4.dist-info/METADATA
odoo14_addon_mis_builder_cash_flow-14.0.1.0.4.dist-info/WHEEL
odoo14_addon_mis_builder_cash_flow-14.0.1.0.4.dist-info/top_level.txt
odoo14_addon_mis_builder_cash_flow-14.0.1.0.4.dist-info/RECORD
